LICENSE.txt
MANIFEST.in
README.md
jenkins-build
keysync
keysync-gui
keysync-gui-folder.spec
keysync-gui-onefile.spec
keysync.desktop
py2app-python2.6.patch
setup.py
icons/add.png
icons/adium.png
icons/chatsecure.png
icons/gajim.png
icons/gnupg.png
icons/irssi.png
icons/jitsi.png
icons/keysync.icns
icons/keysync.ico
icons/keysync.png
icons/kopete.png
icons/pidgin.png
icons/xchat.png
icons/128x128/keysync.png
keysync.egg-info/PKG-INFO
keysync.egg-info/SOURCES.txt
keysync.egg-info/dependency_links.txt
keysync.egg-info/requires.txt
keysync.egg-info/top_level.txt
man/keysync.1
otrapps/__init__.py
otrapps/adium.py
otrapps/chatsecure.py
otrapps/errors.py
otrapps/gajim.py
otrapps/gnupg.py
otrapps/irssi.py
otrapps/jitsi.py
otrapps/kopete.py
otrapps/otr_fingerprints.py
otrapps/otr_private_key.py
otrapps/pidgin.py
otrapps/util.py
otrapps/xchat.py
tests/run-tests.sh
tests/SAMENESS/adium/Accounts.plist
tests/SAMENESS/adium/otr.fingerprints
tests/SAMENESS/adium/otr.private_key
tests/SAMENESS/pidgin/accounts.xml
tests/SAMENESS/pidgin/otr.fingerprints
tests/SAMENESS/pidgin/otr.private_key
tests/adium/Accounts.plist
tests/adium/otr.fingerprints
tests/adium/otr.private_key
tests/adium/Library/Application Support/Adium 2.0/Login Preferences.plist
tests/adium/Library/Application Support/Adium 2.0/Users/Default/AccountPrefs.plist
tests/adium/Library/Application Support/Adium 2.0/Users/Default/Accounts.plist
tests/adium/Library/Application Support/Adium 2.0/Users/Default/ByObjectPrefs.plist
tests/adium/Library/Application Support/Adium 2.0/Users/Default/Contact Alerts.plist
tests/adium/Library/Application Support/Adium 2.0/Users/Default/Contact List.plist
tests/adium/Library/Application Support/Adium 2.0/Users/Default/Event Presets.plist
tests/adium/Library/Application Support/Adium 2.0/Users/Default/General.plist
tests/adium/Library/Application Support/Adium 2.0/Users/Default/List Layout.plist
tests/adium/Library/Application Support/Adium 2.0/Users/Default/List Theme.plist
tests/adium/Library/Application Support/Adium 2.0/Users/Default/Logging.plist
tests/adium/Library/Application Support/Adium 2.0/Users/Default/OTR.plist
